ai_edge_model_explorer_adapter/__init__.py
ai_edge_model_explorer_adapter/_pywrap_convert_wrapper.so
ai_edge_model_explorer_adapter-0.1.14.dist-info/METADATA
ai_edge_model_explorer_adapter-0.1.14.dist-info/WHEEL
ai_edge_model_explorer_adapter-0.1.14.dist-info/top_level.txt
ai_edge_model_explorer_adapter-0.1.14.dist-info/RECORD
